[
  {
    "id": 1,
    "deutsch": "Sekretäre",
    "wissenschaftlich": "Sagittariidae",
    "parentDatei": "14_ordnungen.json",
    "parentId": 8
  },
  {
    "id": 2,
    "deutsch": "Habichtartige",
    "wissenschaftlich": "Accipitridae",
    "parentDatei": "14_ordnungen.json",
    "parentId": 8
  },
  {
    "id": 3,
    "deutsch": "Krallenaffen",
    "wissenschaftlich": "Callitrichidae",
    "parentDatei": "17_ueberfamilien.json",
    "parentId": 2
  },
  {
    "id": 4,
    "deutsch": "Füsiliere",
    "wissenschaftlich": "Caesionidae",
    "parentDatei": "14_ordnungen.json",
    "parentId": 16
  },
  {
    "id": 5,
    "deutsch": "Hammerhaie",
    "wissenschaftlich": "Sphyrnidae",
    "parentDatei": "14_ordnungen.json",
    "parentId": 14
  },
  {
    "id": 6,
    "deutsch": "Spatenfische",
    "wissenschaftlich": "Ephippidae",
    "parentDatei": "14_ordnungen.json",
    "parentId": 17
  },
  {
    "id": 7,
    "deutsch": "Querzahnmolche",
    "wissenschaftlich": "Ambystomatidae",
    "parentDatei": "14_ordnungen.json",
    "parentId": 13
  },
  {
    "id": 8,
    "deutsch": "Menschenaffen",
    "wissenschaftlich": "Hominidae",
    "parentDatei": "17_ueberfamilien.json",
    "parentId": 1
  },
  {
    "id": 9,
    "deutsch": "Meeresschildkröten",
    "wissenschaftlich": "Cheloniidae",
    "parentDatei": "15_unterordnungen.json",
    "parentId": 8
  },
  {
    "id": 10,
    "deutsch": "Elefanten",
    "wissenschaftlich": "Elephantidae",
    "parentDatei": "14_ordnungen.json",
    "parentId": 3
  },
  {
    "id": 11,
    "deutsch": "Requiemhaie",
    "wissenschaftlich": "Carcharhinidae",
    "parentDatei": "14_ordnungen.json",
    "parentId": 14
  },
  {
    "id": 12,
    "deutsch": "Tukane",
    "wissenschaftlich": "Ramphastidae",
    "parentDatei": "14_ordnungen.json",
    "parentId": 10
  },
  {
    "id": 13,
    "deutsch": "Echte Krokodile",
    "wissenschaftlich": "Crocodylidae",
    "parentDatei": "14_ordnungen.json",
    "parentId": 11
  },
  {
    "id": 14,
    "deutsch": "Mondfische",
    "wissenschaftlich": "Molidae",
    "parentDatei": "14_ordnungen.json",
    "parentId": 18
  },
  {
    "id": 15,
    "deutsch": "Hornträger",
    "wissenschaftlich": "Bovidae",
    "parentDatei": "15_unterordnungen.json",
    "parentId": 4
  },
  {
    "id": 16,
    "deutsch": "Katzen",
    "wissenschaftlich": "Felidae",
    "parentDatei": "15_unterordnungen.json",
    "parentId": 1
  },
  {
    "id": 17,
    "deutsch": "Adlerrochen",
    "wissenschaftlich": "Aetobatidae",
    "parentDatei": "14_ordnungen.json",
    "parentId": 15
  },
  {
    "id": 18,
    "deutsch": "Pferde",
    "wissenschaftlich": "Equidae",
    "parentDatei": "15_unterordnungen.json",
    "parentId": 5
  },
  {
    "id": 19,
    "deutsch": "Doktorfische",
    "wissenschaftlich": "Acanthuridae",
    "parentDatei": "14_ordnungen.json",
    "parentId": 17
  },
  {
    "id": 20,
    "deutsch": "Seeadler und Habichte",
    "wissenschaftlich": "Accipitridae",
    "parentDatei": "14_ordnungen.json",
    "parentId": 8
  },
  {
    "id": 21,
    "deutsch": "Kängurus",
    "wissenschaftlich": "Macropodidae",
    "parentDatei": "15_unterordnungen.json",
    "parentId": 7
  },
  {
    "id": 22,
    "deutsch": "Falterfische",
    "wissenschaftlich": "Chaetodontidae",
    "parentDatei": "14_ordnungen.json",
    "parentId": 17
  },
  {
    "id": 23,
    "deutsch": "Hunde",
    "wissenschaftlich": "Canidae",
    "parentDatei": "15_unterordnungen.json",
    "parentId": 2
  },
  {
    "id": 24,
    "deutsch": "Giraffenartige",
    "wissenschaftlich": "Giraffidae",
    "parentDatei": "15_unterordnungen.json",
    "parentId": 4
  },
  {
    "id": 25,
    "deutsch": "Hirsche",
    "wissenschaftlich": "Cervidae",
    "parentDatei": "15_unterordnungen.json",
    "parentId": 4
  },
  {
    "id": 26,
    "deutsch": "Biber",
    "wissenschaftlich": "Castoridae",
    "parentDatei": "15_unterordnungen.json",
    "parentId": 6
  },
  {
    "id": 27,
    "deutsch": "Kugelfische",
    "wissenschaftlich": "Tetraodontidae",
    "parentDatei": "14_ordnungen.json",
    "parentId": 18
  },
  {
    "id": 28,
    "deutsch": "Hornvögel",
    "wissenschaftlich": "Bucerotidae",
    "parentDatei": "14_ordnungen.json",
    "parentId": 9
  }
]